{
    "0": [
        {
            "Id": 1,
            "Script": "_meak_tips_01",
            "Title": "Первая запись в тетради",
            "TitleJp": "ノートの冒頭"
        },
        {
            "Id": 2,
            "Script": "_meak_tips_02",
            "Title": "Размокший дневник",
            "TitleJp": "にじんだ日記"
        },
        {
            "Id": 3,
            "Script": "_meak_tips_03",
            "Title": "Спутанные мысли",
            "TitleJp": "くしゃくしゃの日記"
        },
        {
            "Id": 4,
            "Script": "_meak_tips_04",
            "Title": "21-я страница тетради",
            "TitleJp": "ノート２１ページ"
        },
        {
            "Id": 5,
            "Script": "_meak_tips_05",
            "Title": "24-я страница тетради",
            "TitleJp": "ノート２４ページ"
        },
        {
            "Id": 6,
            "Script": "_meak_tips_06",
            "Title": "Изорванный в клочья",
            "TitleJp": "粉々の日記"
        },
        {
            "Id": 7,
            "Script": "_meak_tips_07",
            "Title": "29-я страница тетради",
            "TitleJp": "ノート２９ページ"
        },
        {
            "Id": 8,
            "Script": "_meak_tips_08",
            "Title": "34-я страница тетради",
            "TitleJp": "ノートの３４ページ"
        },
        {
            "Id": 9,
            "Script": "_meak_tips_09",
            "Title": "42-я страница тетради",
            "TitleJp": "ノートの４２ページ"
        },
        {
            "Id": 10,
            "Script": "_meak_tips_10",
            "Title": "50-я страница тетради",
            "TitleJp": "ノートの５０ページ"
        },
        {
            "Id": 11,
            "Script": "_meak_tips_11",
            "Title": "64-я страница тетради",
            "TitleJp": "ノートの６４ページ"
        },
        {
            "Id": 12,
            "Script": "_meak_tips_12",
            "Title": "85-я страница тетради",
            "TitleJp": "ノートの８５ページ"
        },
        {
            "Id": 13,
            "Script": "_meak_tips_13",
            "Title": "172-я страница тетради",
            "TitleJp": "ノートの１７２ページ"
        },
        {
            "Id": 14,
            "Script": "_meak_tips_14",
            "Title": "173-я страница тетради",
            "TitleJp": "ノートの１７３ページ"
        },
        {
            "Id": 15,
            "Script": "_meak_tips_15",
            "Title": "179-я страница тетради",
            "TitleJp": "ノートの１７９ページ"
        },
        {
            "Id": 16,
            "Script": "_meak_tips_16",
            "Title": "183-я страница тетради",
            "TitleJp": "ノートの１８３ページ"
        },
        {
            "Id": 17,
            "Script": "_meak_tips_17",
            "Title": "185-я страница тетради",
            "TitleJp": "ノートの１８５ページ"
        },
        {
            "Id": 18,
            "Script": "_meak_tips_18",
            "Title": "188-я страница тетради",
            "TitleJp": "ノートの１８８ページ"
        },
        {
            "Id": 19,
            "Script": "_meak_tips_19",
            "Title": "195-я страница тетради",
            "TitleJp": "ノートの１９５ページ"
        },
        {
            "Id": 20,
            "Script": "_meak_tips_20",
            "Title": "196-я страница тетради",
            "TitleJp": "ノートの１９６ページ"
        },
        {
            "Id": 21,
            "Script": "_meak_tips_21",
            "Title": "199-я страница тетради",
            "TitleJp": "ノートの１９９ページ"
        },
        {
            "Id": 22,
            "Script": "_meak_tips_22",
            "Title": "Тетрадь о счастье",
            "TitleJp": "幸せのノート"
        },
        {
            "Id": 23,
            "Script": "_meak_tips_23",
            "Title": "Лишена наследства",
            "TitleJp": "チャンバラで勘当"
        }
    ]
}
